CHANGES.txt
MANIFEST.in
README.txt
setup.cfg
setup.py
src/slapos/__init__.py
src/slapos.recipe.java.egg-info/PKG-INFO
src/slapos.recipe.java.egg-info/SOURCES.txt
src/slapos.recipe.java.egg-info/dependency_links.txt
src/slapos.recipe.java.egg-info/entry_points.txt
src/slapos.recipe.java.egg-info/namespace_packages.txt
src/slapos.recipe.java.egg-info/requires.txt
src/slapos.recipe.java.egg-info/top_level.txt
src/slapos/recipe/__init__.py
src/slapos/recipe/java/__init__.py
src/slapos/recipe/java/recipe.py