Metadata-Version: 1.0
Name: slapos.recipe.java
Version: 0.0.2
Summary: zc.buildout recipe that downloads and installs Java
Home-page: http://www.slapos.org/
Author: Cedric de Saint Martin
Author-email: cedric.dsm@tiolive.com
License: ZPL 2.1
Keywords: buildout java slapos
Platform: UNKNOWN
